aevoo_pycontrol/__init__.py
aevoo_pycontrol/connect.py
aevoo_pycontrol/graphql_client/__init__.py
aevoo_pycontrol/graphql_client/async_base_client.py
aevoo_pycontrol/graphql_client/base_model.py
aevoo_pycontrol/graphql_client/client.py
aevoo_pycontrol/graphql_client/credential_create.py
aevoo_pycontrol/graphql_client/credential_delete.py
aevoo_pycontrol/graphql_client/credential_update.py
aevoo_pycontrol/graphql_client/credentials_list.py
aevoo_pycontrol/graphql_client/enums.py
aevoo_pycontrol/graphql_client/exceptions.py
aevoo_pycontrol/graphql_client/fragments.py
aevoo_pycontrol/graphql_client/input_types.py
aevoo_pycontrol/graphql_client/instance_create.py
aevoo_pycontrol/graphql_client/instance_delete.py
aevoo_pycontrol/graphql_client/instance_disable.py
aevoo_pycontrol/graphql_client/instance_enable.py
aevoo_pycontrol/graphql_client/instance_get.py
aevoo_pycontrol/graphql_client/instance_reload.py
aevoo_pycontrol/graphql_client/instance_secret_get.py
aevoo_pycontrol/graphql_client/instance_start.py
aevoo_pycontrol/graphql_client/instance_stop.py
aevoo_pycontrol/graphql_client/instance_upgrade.py
aevoo_pycontrol/graphql_client/instances_list.py
aevoo_pycontrol/graphql_client/login.py
aevoo_pycontrol/graphql_client/login_target.py
aevoo_pycontrol/graphql_client/logout.py
aevoo_pycontrol/graphql_client/mandate_create.py
aevoo_pycontrol/graphql_client/mandate_revoke.py
aevoo_pycontrol/graphql_client/mandate_status.py
aevoo_pycontrol/graphql_client/mapping_get.py
aevoo_pycontrol/graphql_client/mapping_update.py
aevoo_pycontrol/graphql_client/password_change.py
aevoo_pycontrol/graphql_client/password_reset.py
aevoo_pycontrol/graphql_client/persistent_token_create.py
aevoo_pycontrol/graphql_client/persistent_token_delete.py
aevoo_pycontrol/graphql_client/persistent_token_exist.py
aevoo_pycontrol/graphql_client/person_create.py
aevoo_pycontrol/graphql_client/person_update.py
aevoo_pycontrol/graphql_client/profiles_list.py
aevoo_pycontrol/graphql_client/saas.py
aevoo_pycontrol-0.1.1.dist-info/METADATA
aevoo_pycontrol-0.1.1.dist-info/WHEEL
aevoo_pycontrol-0.1.1.dist-info/RECORD
