Metadata-Version: 2.1
Name: aevoo-pycontrol
Version: 0.1.1
Summary: 
Author: David Casier
Author-email: david.casier@aevoo.fr
Requires-Python: >=3.12,<4.0
Classifier: Programming Language :: Python :: 3
Classifier: Programming Language :: Python :: 3.12
Classifier: Programming Language :: Python :: 3.13
Requires-Dist: PyYAML (>=6.0,<7.0)
Requires-Dist: httpx (>=0.27.2,<0.28.0)
Requires-Dist: pydantic (>=2.11,<3.0)
